{
  "article_id": 1,
  "relations": [
    {
      "subject": "andreas lubitz",
      "relation": "had informed",
      "object": "his lufthansa training school"
    },
    {
      "subject": "andreas lubitz",
      "relation": "had informed",
      "object": "his lufthansa training school of episode"
    },
    {
      "subject": "andreas lubitz",
      "relation": "had informed",
      "object": "his lufthansa training school of episode of depression"
    },
    {
      "subject": "andreas lubitz",
      "relation": "had informed",
      "object": "his lufthansa training school of episode of severe depression"
    }
  ],
  "sentences": [
    {
      "sent_id": 1,
      "text": "marseille prosecutor says `` so far no videos were used in the crash investigation '' despite media reports .journalists at bild and paris match are `` very confident '' the video clip is real , an editor says .andreas lubitz had informed his lufthansa training school of an episode of severe depression , airline says .",
      "tokens": [
        "marseille",
        "prosecutor",
        "says",
        "`",
        "`",
        "so",
        "far",
        "no",
        "videos",
        "were",
        "used",
        "in",
        "the",
        "crash",
        "investigation",
        "''",
        "despite",
        "media",
        "reports",
        ".journalists",
        "at",
        "bild",
        "and",
        "paris",
        "match",
        "are",
        "`",
        "`",
        "very",
        "confident",
        "''",
        "the",
        "video",
        "clip",
        "is",
        "real",
        ",",
        "an",
        "editor",
        "says",
        ".andreas",
        "lubitz",
        "had",
        "informed",
        "his",
        "lufthansa",
        "training",
        "school",
        "of",
        "an",
        "episode",
        "of",
        "severe",
        "depression",
        ",",
        "airline",
        "says",
        "."
      ],
      "pos_tags": [
        "PROPN",
        "NOUN",
        "VERB",
        "PUNCT",
        "PUNCT",
        "ADV",
        "ADV",
        "DET",
        "NOUN",
        "AUX",
        "VERB",
        "ADP",
        "DET",
        "NOUN",
        "NOUN",
        "PUNCT",
        "SCONJ",
        "NOUN",
        "NOUN",
        "NOUN",
        "ADP",
        "PROPN",
        "CCONJ",
        "PROPN",
        "PROPN",
        "AUX",
        "PUNCT",
        "PUNCT",
        "ADV",
        "ADJ",
        "PUNCT",
        "DET",
        "NOUN",
        "NOUN",
        "AUX",
        "ADJ",
        "PUNCT",
        "DET",
        "NOUN",
        "VERB",
        "PUNCT",
        "PROPN",
        "AUX",
        "VERB",
        "DET",
        "NOUN",
        "NOUN",
        "NOUN",
        "ADP",
        "DET",
        "NOUN",
        "ADP",
        "ADJ",
        "NOUN",
        "PUNCT",
        "NOUN",
        "VERB",
        "PUNCT"
      ],
      "is_alpha": [
        true,
        true,
        true,
        false,
        false,
        true,
        true,
        true,
        true,
        true,
        true,
        true,
        true,
        true,
        true,
        false,
        true,
        true,
        true,
        false,
        true,
        true,
        true,
        true,
        true,
        true,
        false,
        false,
        true,
        true,
        false,
        true,
        true,
        true,
        true,
        true,
        false,
        true,
        true,
        true,
        false,
        true,
        true,
        true,
        true,
        true,
        true,
        true,
        true,
        true,
        true,
        true,
        true,
        true,
        false,
        true,
        true,
        false
      ],
      "is_stop": [
        false,
        false,
        false,
        false,
        false,
        true,
        false,
        true,
        false,
        true,
        true,
        true,
        true,
        false,
        false,
        false,
        false,
        false,
        false,
        false,
        true,
        false,
        true,
        false,
        false,
        true,
        false,
        false,
        true,
        false,
        false,
        true,
        false,
        false,
        true,
        false,
        false,
        true,
        false,
        false,
        false,
        false,
        true,
        false,
        true,
        false,
        false,
        false,
        true,
        true,
        false,
        true,
        false,
        false,
        false,
        false,
        false,
        false
      ],
      "entities": [
        [
          "marseille",
          "GPE",
          0,
          9
        ],
        [
          "bild",
          "ORG",
          124,
          128
        ],
        [
          "paris",
          "GPE",
          133,
          138
        ],
        [
          "lubitz",
          "PERSON",
          219,
          225
        ]
      ],
      "chunks": [
        [
          "marseille prosecutor",
          "NP",
          0,
          20
        ],
        [
          "says",
          "VP",
          21,
          25
        ],
        [
          "so far",
          "ADVP",
          29,
          35
        ],
        [
          "no videos",
          "NP",
          36,
          45
        ],
        [
          "were used",
          "VP",
          46,
          55
        ],
        [
          "in",
          "PP",
          56,
          58
        ],
        [
          "the crash investigation",
          "NP",
          59,
          82
        ],
        [
          "despite",
          "PP",
          86,
          93
        ],
        [
          "media reports",
          "NP",
          94,
          107
        ],
        [
          ".journalists",
          "NP",
          108,
          120
        ],
        [
          "at",
          "PP",
          121,
          123
        ],
        [
          "bild and paris match",
          "NP",
          124,
          144
        ],
        [
          "are",
          "VP",
          145,
          148
        ],
        [
          "very confident",
          "ADJP",
          152,
          166
        ],
        [
          "the video clip",
          "NP",
          170,
          184
        ],
        [
          "is",
          "VP",
          185,
          187
        ],
        [
          "real",
          "ADJP",
          188,
          192
        ],
        [
          "an editor",
          "NP",
          195,
          204
        ],
        [
          "says",
          "VP",
          205,
          209
        ],
        [
          "lubitz",
          "NP",
          219,
          225
        ],
        [
          "had informed",
          "VP",
          226,
          238
        ],
        [
          "his lufthansa training school",
          "NP",
          239,
          268
        ],
        [
          "of",
          "PP",
          269,
          271
        ],
        [
          "an episode",
          "NP",
          272,
          282
        ],
        [
          "of",
          "PP",
          283,
          285
        ],
        [
          "severe depression",
          "NP",
          286,
          303
        ],
        [
          "airline",
          "NP",
          306,
          313
        ],
        [
          "says",
          "VP",
          314,
          318
        ]
      ],
      "frames": [
        [
          "says",
          "say.01"
        ],
        [
          "were",
          "be.03"
        ],
        [
          "used",
          "use.01"
        ],
        [
          "reports",
          "report.01"
        ],
        [
          "are",
          "be.01"
        ],
        [
          "is",
          "be.01"
        ],
        [
          "says",
          "say.01"
        ],
        [
          "had",
          "have.01"
        ],
        [
          "informed",
          "inform.01"
        ],
        [
          "depression",
          "depress.01"
        ],
        [
          "says",
          "say.01"
        ]
      ],
      "tokens_det": [
        {
          "id": 1,
          "token": "marseille",
          "pos_tags": "PROPN",
          "is_alpha": true,
          "is_stop": false,
          "aligned_to": 37
        },
        {
          "id": 2,
          "token": "prosecutor",
          "pos_tags": "NOUN",
          "is_alpha": true,
          "is_stop": false,
          "aligned_to": 38
        },
        {
          "id": 3,
          "token": "says",
          "pos_tags": "VERB",
          "is_alpha": true,
          "is_stop": false,
          "aligned_to": []
        },
        {
          "id": 4,
          "token": "`",
          "pos_tags": "PUNCT",
          "is_alpha": false,
          "is_stop": false,
          "aligned_to": 44
        },
        {
          "id": 5,
          "token": "`",
          "pos_tags": "PUNCT",
          "is_alpha": false,
          "is_stop": false,
          "aligned_to": 45
        },
        {
          "id": 6,
          "token": "so",
          "pos_tags": "ADV",
          "is_alpha": true,
          "is_stop": true,
          "aligned_to": 46
        },
        {
          "id": 7,
          "token": "far",
          "pos_tags": "ADV",
          "is_alpha": true,
          "is_stop": false,
          "aligned_to": 47
        },
        {
          "id": 8,
          "token": "no",
          "pos_tags": "DET",
          "is_alpha": true,
          "is_stop": true,
          "aligned_to": 48
        },
        {
          "id": 9,
          "token": "videos",
          "pos_tags": "NOUN",
          "is_alpha": true,
          "is_stop": false,
          "aligned_to": 49
        },
        {
          "id": 10,
          "token": "were",
          "pos_tags": "AUX",
          "is_alpha": true,
          "is_stop": true,
          "aligned_to": 50
        },
        {
          "id": 11,
          "token": "used",
          "pos_tags": "VERB",
          "is_alpha": true,
          "is_stop": true,
          "aligned_to": 51
        },
        {
          "id": 12,
          "token": "in",
          "pos_tags": "ADP",
          "is_alpha": true,
          "is_stop": true,
          "aligned_to": 52
        },
        {
          "id": 13,
          "token": "the",
          "pos_tags": "DET",
          "is_alpha": true,
          "is_stop": true,
          "aligned_to": 53
        },
        {
          "id": 14,
          "token": "crash",
          "pos_tags": "NOUN",
          "is_alpha": true,
          "is_stop": false,
          "aligned_to": 54
        },
        {
          "id": 15,
          "token": "investigation",
          "pos_tags": "NOUN",
          "is_alpha": true,
          "is_stop": false,
          "aligned_to": 181
        },
        {
          "id": 16,
          "token": "''",
          "pos_tags": "PUNCT",
          "is_alpha": false,
          "is_stop": false,
          "aligned_to": 262
        },
        {
          "id": 17,
          "token": "despite",
          "pos_tags": "SCONJ",
          "is_alpha": true,
          "is_stop": false,
          "aligned_to": []
        },
        {
          "id": 18,
          "token": "media",
          "pos_tags": "NOUN",
          "is_alpha": true,
          "is_stop": false,
          "aligned_to": []
        },
        {
          "id": 19,
          "token": "reports",
          "pos_tags": "NOUN",
          "is_alpha": true,
          "is_stop": false,
          "aligned_to": 329
        },
        {
          "id": 20,
          "token": ".journalists",
          "pos_tags": "NOUN",
          "is_alpha": false,
          "is_stop": false,
          "aligned_to": []
        },
        {
          "id": 21,
          "token": "at",
          "pos_tags": "ADP",
          "is_alpha": true,
          "is_stop": true,
          "aligned_to": 347
        },
        {
          "id": 22,
          "token": "bild",
          "pos_tags": "PROPN",
          "is_alpha": true,
          "is_stop": false,
          "aligned_to": 477
        },
        {
          "id": 23,
          "token": "and",
          "pos_tags": "CCONJ",
          "is_alpha": true,
          "is_stop": true,
          "aligned_to": 478
        },
        {
          "id": 24,
          "token": "paris",
          "pos_tags": "PROPN",
          "is_alpha": true,
          "is_stop": false,
          "aligned_to": 479
        },
        {
          "id": 25,
          "token": "match",
          "pos_tags": "PROPN",
          "is_alpha": true,
          "is_stop": false,
          "aligned_to": 480
        },
        {
          "id": 26,
          "token": "are",
          "pos_tags": "AUX",
          "is_alpha": true,
          "is_stop": true,
          "aligned_to": 481
        },
        {
          "id": 27,
          "token": "`",
          "pos_tags": "PUNCT",
          "is_alpha": false,
          "is_stop": false,
          "aligned_to": 482
        },
        {
          "id": 28,
          "token": "`",
          "pos_tags": "PUNCT",
          "is_alpha": false,
          "is_stop": false,
          "aligned_to": 483
        },
        {
          "id": 29,
          "token": "very",
          "pos_tags": "ADV",
          "is_alpha": true,
          "is_stop": true,
          "aligned_to": 484
        },
        {
          "id": 30,
          "token": "confident",
          "pos_tags": "ADJ",
          "is_alpha": true,
          "is_stop": false,
          "aligned_to": 485
        },
        {
          "id": 31,
          "token": "''",
          "pos_tags": "PUNCT",
          "is_alpha": false,
          "is_stop": false,
          "aligned_to": 486
        },
        {
          "id": 32,
          "token": "the",
          "pos_tags": "DET",
          "is_alpha": true,
          "is_stop": true,
          "aligned_to": []
        },
        {
          "id": 33,
          "token": "video",
          "pos_tags": "NOUN",
          "is_alpha": true,
          "is_stop": false,
          "aligned_to": []
        },
        {
          "id": 34,
          "token": "clip",
          "pos_tags": "NOUN",
          "is_alpha": true,
          "is_stop": false,
          "aligned_to": 489
        },
        {
          "id": 35,
          "token": "is",
          "pos_tags": "AUX",
          "is_alpha": true,
          "is_stop": true,
          "aligned_to": 490
        },
        {
          "id": 36,
          "token": "real",
          "pos_tags": "ADJ",
          "is_alpha": true,
          "is_stop": false,
          "aligned_to": 491
        },
        {
          "id": 37,
          "token": ",",
          "pos_tags": "PUNCT",
          "is_alpha": false,
          "is_stop": false,
          "aligned_to": 547
        },
        {
          "id": 38,
          "token": "an",
          "pos_tags": "DET",
          "is_alpha": true,
          "is_stop": true,
          "aligned_to": []
        },
        {
          "id": 39,
          "token": "editor",
          "pos_tags": "NOUN",
          "is_alpha": true,
          "is_stop": false,
          "aligned_to": []
        },
        {
          "id": 40,
          "token": "says",
          "pos_tags": "VERB",
          "is_alpha": true,
          "is_stop": false,
          "aligned_to": []
        },
        {
          "id": 41,
          "token": ".andreas",
          "pos_tags": "PUNCT",
          "is_alpha": false,
          "is_stop": false,
          "aligned_to": []
        },
        {
          "id": 42,
          "token": "lubitz",
          "pos_tags": "PROPN",
          "is_alpha": true,
          "is_stop": false,
          "aligned_to": 572
        },
        {
          "id": 43,
          "token": "had",
          "pos_tags": "AUX",
          "is_alpha": true,
          "is_stop": true,
          "aligned_to": 573
        },
        {
          "id": 44,
          "token": "informed",
          "pos_tags": "VERB",
          "is_alpha": true,
          "is_stop": false,
          "aligned_to": []
        },
        {
          "id": 45,
          "token": "his",
          "pos_tags": "DET",
          "is_alpha": true,
          "is_stop": true,
          "aligned_to": 603
        },
        {
          "id": 46,
          "token": "lufthansa",
          "pos_tags": "NOUN",
          "is_alpha": true,
          "is_stop": false,
          "aligned_to": 604
        },
        {
          "id": 47,
          "token": "training",
          "pos_tags": "NOUN",
          "is_alpha": true,
          "is_stop": false,
          "aligned_to": 606
        },
        {
          "id": 48,
          "token": "school",
          "pos_tags": "NOUN",
          "is_alpha": true,
          "is_stop": false,
          "aligned_to": 607
        },
        {
          "id": 49,
          "token": "of",
          "pos_tags": "ADP",
          "is_alpha": true,
          "is_stop": true,
          "aligned_to": []
        },
        {
          "id": 50,
          "token": "an",
          "pos_tags": "DET",
          "is_alpha": true,
          "is_stop": true,
          "aligned_to": []
        },
        {
          "id": 51,
          "token": "episode",
          "pos_tags": "NOUN",
          "is_alpha": true,
          "is_stop": false,
          "aligned_to": 617
        },
        {
          "id": 52,
          "token": "of",
          "pos_tags": "ADP",
          "is_alpha": true,
          "is_stop": true,
          "aligned_to": 618
        },
        {
          "id": 53,
          "token": "severe",
          "pos_tags": "ADJ",
          "is_alpha": true,
          "is_stop": false,
          "aligned_to": 619
        },
        {
          "id": 54,
          "token": "depression",
          "pos_tags": "NOUN",
          "is_alpha": true,
          "is_stop": false,
          "aligned_to": 620
        },
        {
          "id": 55,
          "token": ",",
          "pos_tags": "PUNCT",
          "is_alpha": false,
          "is_stop": false,
          "aligned_to": 621
        },
        {
          "id": 56,
          "token": "airline",
          "pos_tags": "NOUN",
          "is_alpha": true,
          "is_stop": false,
          "aligned_to": 624
        },
        {
          "id": 57,
          "token": "says",
          "pos_tags": "VERB",
          "is_alpha": true,
          "is_stop": false,
          "aligned_to": []
        },
        {
          "id": 58,
          "token": ".",
          "pos_tags": "PUNCT",
          "is_alpha": false,
          "is_stop": false,
          "aligned_to": 1355
        }
      ]
    }
  ],
  "alignment": [
    [
      1,
      37
    ],
    [
      2,
      38
    ],
    [
      4,
      44
    ],
    [
      5,
      45
    ],
    [
      6,
      46
    ],
    [
      7,
      47
    ],
    [
      8,
      48
    ],
    [
      9,
      49
    ],
    [
      10,
      50
    ],
    [
      11,
      51
    ],
    [
      12,
      52
    ],
    [
      13,
      53
    ],
    [
      14,
      54
    ],
    [
      15,
      181
    ],
    [
      16,
      262
    ],
    [
      19,
      329
    ],
    [
      21,
      347
    ],
    [
      22,
      477
    ],
    [
      23,
      478
    ],
    [
      24,
      479
    ],
    [
      25,
      480
    ],
    [
      26,
      481
    ],
    [
      27,
      482
    ],
    [
      28,
      483
    ],
    [
      29,
      484
    ],
    [
      30,
      485
    ],
    [
      31,
      486
    ],
    [
      34,
      489
    ],
    [
      35,
      490
    ],
    [
      36,
      491
    ],
    [
      37,
      547
    ],
    [
      42,
      572
    ],
    [
      43,
      573
    ],
    [
      45,
      603
    ],
    [
      46,
      604
    ],
    [
      47,
      606
    ],
    [
      48,
      607
    ],
    [
      51,
      617
    ],
    [
      52,
      618
    ],
    [
      53,
      619
    ],
    [
      54,
      620
    ],
    [
      55,
      621
    ],
    [
      56,
      624
    ],
    [
      58,
      1355
    ]
  ],
  "commonWords": [
    {
      "token": "marseille",
      "freq": 1
    },
    {
      "token": "prosecutor",
      "freq": 1
    },
    {
      "token": "far",
      "freq": 1
    },
    {
      "token": "videos",
      "freq": 1
    },
    {
      "token": "crash",
      "freq": 1
    },
    {
      "token": "investigation",
      "freq": 1
    },
    {
      "token": "media",
      "freq": 1
    },
    {
      "token": "reports",
      "freq": 1
    },
    {
      "token": "bild",
      "freq": 1
    },
    {
      "token": "paris",
      "freq": 1
    },
    {
      "token": "match",
      "freq": 1
    },
    {
      "token": "confident",
      "freq": 1
    },
    {
      "token": "video",
      "freq": 1
    },
    {
      "token": "clip",
      "freq": 1
    },
    {
      "token": "real",
      "freq": 1
    },
    {
      "token": "editor",
      "freq": 1
    },
    {
      "token": "lubitz",
      "freq": 1
    },
    {
      "token": "lufthansa",
      "freq": 1
    },
    {
      "token": "training",
      "freq": 1
    },
    {
      "token": "school",
      "freq": 1
    },
    {
      "token": "episode",
      "freq": 1
    },
    {
      "token": "severe",
      "freq": 1
    },
    {
      "token": "depression",
      "freq": 1
    },
    {
      "token": "airline",
      "freq": 1
    }
  ],
  "novelWords": [
    {
      "token": "says",
      "freq": 3
    },
    {
      "token": "despite",
      "freq": 1
    },
    {
      "token": "informed",
      "freq": 1
    }
  ]
}